{
    "name": "Re:Avaritia",
    "description": "A reforge version of Avaritia",
    "logo": "avaritia2.webp",
    "mod_meta": {
        "id": "avaritia",
        "package": "committee.nova.mods.avaritia",
        "license": "MIT"
    },
    "ids": {
        "gh": "Nova-Committee/Re-Avaritia",
        "cf": "623969",
        "mr": "QeB3NRC5"
    },
    "tags": [
        "Adventure",
        "Equipment"
    ],
    "versions": {
        "1.18.2": {
            "Fabric": "None",
            "Forge": "Ended"
        },
        "1.19.2": {
            "Fabric": "None",
            "Forge": "Ended"
        },
        "1.19.4": {
            "Fabric": "None",
            "Forge": "Ended"
        },
        "1.20.1": {
            "Fabric": "Partly",
            "Forge": "All",
            "NeoForge": "All"
        },
        "1.20.4": {
            "Fabric": "None",
            "Forge": "None",
            "NeoForge": "Partly"
        },
        "1.21.1": {
            "Fabric": "None",
            "Forge": "None",
            "NeoForge": "Partly"
        }
    },
    "status": "Maintaining",
    "coop": [
        "cnlimiter"
    ]
}